tee_output/__init__.py
tee_output-0.4.16.data/scripts/parent-lifetime
tee_output-0.4.16.dist-info/METADATA
tee_output-0.4.16.dist-info/WHEEL
tee_output-0.4.16.dist-info/top_level.txt
tee_output-0.4.16.dist-info/RECORD
